{"format":2,"version":"6.0.2","globals":"6a4256e35f9798f9bb080b10ccdeeac8","files":{"d_7b071bdc2a35fa80___init___py":{"hash":"1fc4f9498f460d6c93280e8962ee0c0f","index":{"nums":[2,1,2,0,0,0,0,0],"html_filename":"d_7b071bdc2a35fa80___init___py.html","relative_filename":"cogapp/__init__.py"}},"d_7b071bdc2a35fa80___main___py":{"hash":"ffe6befa655d4d0b0b31eb0c73811311","index":{"nums":[2,1,3,0,3,0,0,0],"html_filename":"d_7b071bdc2a35fa80___main___py.html","relative_filename":"cogapp/__main__.py"}},"d_7b071bdc2a35fa80_backward_py":{"hash":"32afb71b2a11dd4b8ca4ed66b6815d42","index":{"nums":[2,1,22,0,6,4,2,2],"html_filename":"d_7b071bdc2a35fa80_backward_py.html","relative_filename":"cogapp/backward.py"}},"d_7b071bdc2a35fa80_cogapp_py":{"hash":"f3523a775c5c1d12a213eead8df82291","index":{"nums":[2,1,486,1,215,200,28,132],"html_filename":"d_7b071bdc2a35fa80_cogapp_py.html","relative_filename":"cogapp/cogapp.py"}},"d_7b071bdc2a35fa80_makefiles_py":{"hash":"85ec1064ff86d94238a8d7b76a2178a5","index":{"nums":[2,1,27,0,20,14,0,14],"html_filename":"d_7b071bdc2a35fa80_makefiles_py.html","relative_filename":"cogapp/makefiles.py"}},"d_7b071bdc2a35fa80_test_cogapp_py":{"hash":"6985a05ab5a9b347b3665136686f6fb1","index":{"nums":[2,1,788,8,547,20,0,18],"html_filename":"d_7b071bdc2a35fa80_test_cogapp_py.html","relative_filename":"cogapp/test_cogapp.py"}},"d_7b071bdc2a35fa80_test_makefiles_py":{"hash":"647f7dc911c97a6e646a91c3300a25ff","index":{"nums":[2,1,71,0,53,6,0,6],"html_filename":"d_7b071bdc2a35fa80_test_makefiles_py.html","relative_filename":"cogapp/test_makefiles.py"}},"d_7b071bdc2a35fa80_test_whiteutils_py":{"hash":"9476b26e42e6169b1857cfe7f29bf954","index":{"nums":[2,1,69,0,50,0,0,0],"html_filename":"d_7b071bdc2a35fa80_test_whiteutils_py.html","relative_filename":"cogapp/test_whiteutils.py"}},"d_7b071bdc2a35fa80_whiteutils_py":{"hash":"cf00c3e6149e4b80a2d01b6919c066a4","index":{"nums":[2,1,45,0,5,34,4,4],"html_filename":"d_7b071bdc2a35fa80_whiteutils_py.html","relative_filename":"cogapp/whiteutils.py"}}}}